pyonelab/__about__.py
pyonelab/__init__.py
pyonelab/main.py
pyonelab-Darwin/__about__.py
pyonelab-Darwin/__init__.py
pyonelab-Darwin/main.py
pyonelab-Linux/__about__.py
pyonelab-Linux/__init__.py
pyonelab-Linux/main.py
pyonelab-Linux/bin/Linux/getdp
pyonelab-Linux/bin/Linux/gmsh
pyonelab-Windows/__about__.py
pyonelab-Windows/__init__.py
pyonelab-Windows/main.py
pyonelab-1.0.5.dist-info/LICENCE.txt
pyonelab-1.0.5.dist-info/METADATA
pyonelab-1.0.5.dist-info/WHEEL
pyonelab-1.0.5.dist-info/top_level.txt
pyonelab-1.0.5.dist-info/RECORD
