Metadata-Version: 2.1
Name: pyonelab
Version: 1.0.5
Summary: Onelab (Gmsh and GetDP) for your OS, from Python.
Home-page: https://github.com/benvial/pyonelab
Author: Benjamin Vial
Author-email: benjamin.vial84@gmail.com
License: License :: OSI Approved :: MIT License
Project-URL: Documentation, https://github.com/benvial/pyonelab
Platform: any
Classifier: Development Status :: 5 - Production/Stable
Classifier: License :: OSI Approved :: MIT License
Classifier: Intended Audience :: Science/Research
Classifier: Operating System :: OS Independent
Classifier: Programming Language :: Python
Classifier: Programming Language :: Python :: 3
Classifier: Topic :: Scientific/Engineering :: Mathematics
License-File: LICENCE.txt
